AUTHORS.rst
CONTRIBUTING.rst
HISTORY.rst
LICENSE
MANIFEST.in
README.rst
setup.cfg
setup.py
course_backup/__init__.py
course_backup/course_backup.py
course_backup.egg-info/PKG-INFO
course_backup.egg-info/SOURCES.txt
course_backup.egg-info/dependency_links.txt
course_backup.egg-info/entry_points.txt
course_backup.egg-info/not-zip-safe
course_backup.egg-info/requires.txt
course_backup.egg-info/top_level.txt
docs/Makefile
docs/authors.rst
docs/conf.py
docs/contributing.rst
docs/history.rst
docs/index.rst
docs/installation.rst
docs/make.bat
docs/readme.rst
docs/usage.rst
tests/__init__.py
tests/test_course_backup.py