Metadata-Version: 1.1
Name: course-backup
Version: 0.1.3
Summary: backup open edx courses
Home-page: https://github.com/wwj718/course_backup
Author: wenjie wu
Author-email: wuwenjie718@gmail.com
License: ISCL
Keywords: course_backup
Platform: UNKNOWN
Classifier: Development Status :: 2 - Pre-Alpha
Classifier: Intended Audience :: Developers
Classifier: License :: OSI Approved :: ISC License (ISCL)
Classifier: Natural Language :: English
Classifier: Programming Language :: Python :: 2
Classifier: Programming Language :: Python :: 2.6
Classifier: Programming Language :: Python :: 2.7
Classifier: Programming Language :: Python :: 3
Classifier: Programming Language :: Python :: 3.3
Classifier: Programming Language :: Python :: 3.4
Classifier: Programming Language :: Python :: 3.5
